bitbully/__init__.py
bitbully/agent_interface.py
bitbully/bitbully_core.cpython-313-x86_64-linux-musl.so
bitbully/bitbully_core.pyi
bitbully/board.py
bitbully/gui_c4.py
bitbully/libcppBitBully.a
bitbully/solver.py
bitbully/assets/empty.png
bitbully/assets/empty_m.png
bitbully/assets/empty_r.png
bitbully/assets/red.png
bitbully/assets/red_m.png
bitbully/assets/yellow.png
bitbully/assets/yellow_m.png
bitbully.libs/libgcc_s-0cd532bd.so.1
bitbully.libs/libstdc++-5d72f927.so.6.0.33
bitbully-0.0.75.dist-info/METADATA
bitbully-0.0.75.dist-info/WHEEL
bitbully-0.0.75.dist-info/top_level.txt
bitbully-0.0.75.dist-info/RECORD
bitbully-0.0.75.dist-info/licenses/LICENSE
bitbully-0.0.75.dist-info/sboms/auditwheel.cdx.json
