Metadata-Version: 2.4
Name: bitbully
Version: 0.0.75
Summary: A fast Connect-4 Solver for Python & C++
Author: Markus Thill
Maintainer: Markus Thill
License:                     GNU AFFERO GENERAL PUBLIC LICENSE
Project-URL: Homepage, https://github.com/MarkusThill/BitBully
Project-URL: Issues, https://github.com/MarkusThill/BitBully/issues
Keywords: connect-4,solver,perfect-playing,opening book,tree-search
Classifier: Programming Language :: Python :: 3
Classifier: Programming Language :: C++
Classifier: Programming Language :: Python :: Implementation :: CPython
Requires-Python: >=3.10
License-File: LICENSE
Requires-Dist: bitbully-databases
Provides-Extra: dev
Requires-Dist: commitizen; extra == "dev"
Requires-Dist: pre-commit; extra == "dev"
Requires-Dist: build; extra == "dev"
Requires-Dist: twine; extra == "dev"
Requires-Dist: readme_renderer[md]; extra == "dev"
Requires-Dist: keyrings.alt; extra == "dev"
Requires-Dist: pre-commit; extra == "dev"
Requires-Dist: pydoclint; extra == "dev"
Requires-Dist: mkdocs; extra == "dev"
Requires-Dist: mkdocstrings[python]; extra == "dev"
Requires-Dist: mkdocs-material; extra == "dev"
Requires-Dist: pyrefly; extra == "dev"
Requires-Dist: pytest; extra == "dev"
Requires-Dist: pytest-cov; extra == "dev"
Requires-Dist: ruff; extra == "dev"
Provides-Extra: gui
Requires-Dist: matplotlib; extra == "gui"
Requires-Dist: ipywidgets; extra == "gui"
Requires-Dist: ipympl; extra == "gui"
Provides-Extra: ci
Requires-Dist: pytest; extra == "ci"
Requires-Dist: ruff; extra == "ci"
Dynamic: license-file
